<?xml version="1.0" encoding="utf-8"?>
<root>
	<status>success</status>
	<message>The COVERAGE field for indicator 4-b-1, translated into all languages</message>
	<data>
		<languages>
			<language lang="ar"/>
			<language lang="en">&lt;h1&gt;Data availability&lt;/h1&gt;
&lt;h2&gt;Description:&lt;/h2&gt;
&lt;p&gt;On a recipient basis for all developing countries eligible for ODA.&lt;/p&gt;
&lt;h2&gt;Time series:&lt;/h2&gt;
&lt;p&gt;Data are available from 2010.&lt;/p&gt;
&lt;h2&gt;Disaggregation:&lt;/h2&gt;
&lt;p&gt;This indicator can be disaggregated by donor, recipient country, type of finance, etc.&lt;/p&gt;
			</language>
			<language lang="es">&lt;h1&gt;Disponibilidad de datos&lt;/h1&gt;
&lt;h2&gt;Descripción:&lt;/h2&gt;
&lt;p&gt;Sobre la base de los receptores para todos los países en desarrollo que pueden recibir AOD.&lt;/p&gt;
&lt;h2&gt;Series temporales:&lt;/h2&gt;
&lt;p&gt;Los datos están disponibles desde 2010.&lt;/p&gt;
&lt;h2&gt;Desagregación:&lt;/h2&gt;
&lt;p&gt;Este indicador puede desglosarse por donante, país receptor, tipo de financiación, etc.&lt;/p&gt;
			</language>
			<language lang="fr">&lt;h1&gt;Disponibilité des données &lt;/h1&gt;
&lt;h2&gt;Description : &lt;/h2&gt;
&lt;p&gt;Sur la base du bénéficiaire pour tous les pays en développement éligibles à l&apos;APD.&lt;/p&gt;
&lt;h2&gt;Séries chronologiques : &lt;/h2&gt;
&lt;p&gt;Les données sont disponibles à partir de 2010.&lt;/p&gt;
&lt;h2&gt;Désagrégation:&lt;/h2&gt;
&lt;p&gt;Cet indicateur peut être ventilé par donateur, pays bénéficiaire, type de financement, etc.&lt;/p&gt;
			</language>
			<language lang="ru"/>
</languages>
</data>
</root>
