<?xml version="1.0" encoding="utf-8"?>
<root>
	<status>success</status>
	<message>The IMPUTATION field for indicator 11-b-2, translated into all languages</message>
	<data>
		<languages>
			<language lang="ar"/>
			<language lang="en">&lt;p&gt;&lt;strong&gt;&amp;#x2022; At country level&lt;/strong&gt;&lt;/p&gt;
&lt;p&gt;If a country does not report (missing Value), it will be considered to be 0 or null as same as the HFA Monitor.&lt;/p&gt;
&lt;p&gt;&lt;strong&gt;&amp;#x2022; At regional and global levels&lt;/strong&gt;&lt;/p&gt;
&lt;p&gt;NA&lt;/p&gt;
			</language>
			<language lang="es"/>
			<language lang="fr"/>
			<language lang="pt"/>
			<language lang="ru"/>
</languages>
</data>
</root>
