<?xml version="1.0" encoding="utf-8"?>
<root>
	<status>success</status>
	<message>The QUALITY_ASSMNT field for indicator 4-c-1, translated into all languages</message>
	<data>
		<languages>
			<language lang="ar"/>
			<language lang="en">&lt;p&gt;Accurate data on the number of teachers at each level of education who have the minimum required qualifications and the total number of teachers at each level in a given academic year are essential for calculating this indicator. Criteria for quality assessment include: data sources must include proper documentation; data values must be representative at the national population level and, if not, should be footnoted; data are plausible and based on trends and consistency with previously published/reported values for the indicator. &lt;/p&gt;
			</language>
			<language lang="es"/>
			<language lang="fr">&lt;p&gt;Des données précises sur le nombre d’enseignants à chaque niveau d’enseignement qui ont les qualifications minimales requises et le nombre total d’enseignants à chaque niveau au cours d’une année scolaire donnée sont essentielles pour calculer cet indicateur. Les critères d’évaluation de la qualité comprennent : les sources de données doivent comprendre la documentation appropriée; les valeurs des données doivent être représentatives au niveau de la population nationale et, dans la négative, doivent être notées en bas de page; les données sont plausibles et fondées sur des tendances et sont cohérentes avec les valeurs précédemment publiées ou déclarées pour l’indicateur. &lt;/p&gt;
			</language>
			<language lang="pt"/>
			<language lang="ru"/>
</languages>
</data>
</root>
