<?xml version="1.0" encoding="utf-8"?>
<root>
	<status>success</status>
	<message>The SDG_INDICATOR field for indicator 2-a-1, translated into all languages</message>
	<data>
		<languages>
			<language lang="ar"/>
			<language lang="en">&lt;p&gt;Indicator 2.a.1: The agriculture orientation index for government expenditures&lt;/p&gt;
			</language>
			<language lang="es">&lt;p&gt;Indicador 2.a.1: Índice de orientación agrícola para el gasto público&lt;/p&gt;
			</language>
			<language lang="fr">&lt;p&gt;Indicateur 2.a.1 : Indice d’orientation agricole des dépenses publiques&lt;/p&gt;
			</language>
			<language lang="pt"/>
			<language lang="ru">&lt;p&gt;Показатель 2.a.1: Индекс ориентированности на сельское хозяйство, определяемый по структуре государственных расходов&lt;/p&gt;
			</language>
</languages>
</data>
</root>
