<?xml version="1.0" encoding="utf-8"?>
<root>
	<status>success</status>
	<message>The OTHER_DOC field for indicator 4-6-1, translated into all languages</message>
	<data>
		<languages>
			<language lang="ar"/>
			<language lang="en">&lt;p&gt;&lt;strong&gt;URL:&lt;/strong&gt;&lt;/p&gt;
&lt;p&gt;http://www.uis.unesco.org/Pages/default.aspx&lt;/p&gt;
&lt;p&gt;&lt;strong&gt;References:&lt;/strong&gt;&lt;/p&gt;
&lt;p&gt;Programme for the International Assessment of Adult Competencies (PIAAC): &lt;/p&gt;
&lt;p&gt;http://www.oecd.org/site/piaac/ &lt;/p&gt;
&lt;p&gt;STEP Skills Measurement Programme: http://microdata.worldbank.org/index.php/catalog/step/about &lt;/p&gt;
&lt;p&gt;Action Research: Measuring Literacy Programme Participants&amp;#x2019; Learning Outcomes (RAMAA): &lt;/p&gt;
&lt;p&gt;https://uil.unesco.org/literacy-and-basic-skills/assessment-and-monitoring-ramaa&lt;/p&gt;
			</language>
			<language lang="es"/>
			<language lang="fr"/>
			<language lang="pt"/>
			<language lang="ru"/>
</languages>
</data>
</root>
