{"status":"success","message":"The RATIONALE field for indicator 17-10-1, translated into all languages","data":{"ar":"","en":"<h2>Rationale:</h2>\n<p>The average level of customs tariff rates applied worldwide can be used as an indicator of the degree of success achieved by multilateral negotiations and regional trade agreements.</p>","es":"","fr":"","ru":"<h2>Обоснование:</h2>\n<p>Средний уровень ставок таможенных тарифов, применяемых во всем мире, можно использовать как показатель степени успеха, достигнутого в ходе многосторонних переговоров и в реализации региональных торговых соглашений.</p>"}}