<?xml version="1.0" encoding="utf-8"?>
<root>
	<status>success</status>
	<message>The COVERAGE field for indicator 16-2-2, translated into all languages</message>
	<data>
		<languages>
			<language lang="ar"/>
			<language lang="en">&lt;p&gt;&lt;strong&gt;Data availability:&lt;/strong&gt;&lt;/p&gt;
&lt;p&gt;Currently the United Nations Office on Drugs and Crime (UNODC) has regular data collection on detected victims of trafficking in persons for about 140 countries.&lt;/p&gt;
&lt;p&gt;&lt;strong&gt;Time series:&lt;/strong&gt;&lt;/p&gt;
&lt;p&gt;Information available since 2003 (limited to detected victims of trafficking).&lt;/p&gt;
&lt;p&gt;&lt;strong&gt;Disaggregation:&lt;/strong&gt;&lt;/p&gt;
&lt;p&gt;Recommended disaggregations for this indicator are:&lt;/p&gt;
&lt;p&gt;- sex of victims&lt;/p&gt;
&lt;p&gt;- age of victims&lt;/p&gt;
&lt;p&gt;- form of exploitation&lt;/p&gt;
			</language>
			<language lang="es"/>
			<language lang="fr"/>
			<language lang="pt"/>
			<language lang="ru"/>
</languages>
</data>
</root>
