{"status":"success","message":"The COVERAGE field for indicator 2-3-2, translated into all languages","data":{"ar":"","en":"<p><strong>Data availability:</strong></p>\n<p>Data is still not available in a systematic and harmonized fashion. The following data availability information is provided based on available suitable surveys in selected countries. </p>\n<p>Breakdown of the number of countries covered by region is as follows:</p>\n<table>\n  <tbody>\n    <tr>\n      <td></td>\n      <td>\n        <p>Number of countries</p>\n      </td>\n      <td>\n        <p>Nature of data</p>\n      </td>\n    </tr>\n    <tr>\n      <td>\n        <p>World</p>\n      </td>\n      <td>\n        <p>36</p>\n      </td>\n      <td>\n        <p>E</p>\n      </td>\n    </tr>\n    <tr>\n      <td>\n        <p>Africa</p>\n      </td>\n      <td>\n        <p>15</p>\n      </td>\n      <td>\n        <p>E</p>\n      </td>\n    </tr>\n    <tr>\n      <td>\n        <p>Northern Africa</p>\n      </td>\n      <td></td>\n      <td></td>\n    </tr>\n    <tr>\n      <td>\n        <p>Sub-Saharan Africa</p>\n      </td>\n      <td></td>\n      <td></td>\n    </tr>\n    <tr>\n      <td>\n        <p>Eastern Africa</p>\n      </td>\n      <td>\n        <p>5</p>\n      </td>\n      <td>\n        <p>E</p>\n      </td>\n    </tr>\n    <tr>\n      <td>\n        <p>Middle Africa</p>\n      </td>\n      <td>\n        <p>1</p>\n      </td>\n      <td>\n        <p>E</p>\n      </td>\n    </tr>\n    <tr>\n      <td>\n        <p>Southern Africa</p>\n      </td>\n      <td>\n        <p>1</p>\n      </td>\n      <td>\n        <p>E</p>\n      </td>\n    </tr>\n    <tr>\n      <td>\n        <p>Western Africa</p>\n      </td>\n      <td>\n        <p>8</p>\n      </td>\n      <td>\n        <p>E</p>\n      </td>\n    </tr>\n    <tr>\n      <td>\n        <p>Americas</p>\n      </td>\n      <td>\n        <p>7</p>\n      </td>\n      <td>\n        <p>E</p>\n      </td>\n    </tr>\n    <tr>\n      <td>\n        <p>Latin America and the Caribbean</p>\n      </td>\n      <td></td>\n      <td></td>\n    </tr>\n    <tr>\n      <td>\n        <p>Caribbean</p>\n      </td>\n      <td></td>\n      <td></td>\n    </tr>\n    <tr>\n      <td>\n        <p>Latin America</p>\n      </td>\n      <td>\n        <p>3</p>\n      </td>\n      <td>\n        <p>E</p>\n      </td>\n    </tr>\n    <tr>\n      <td>\n        <p>Northern America</p>\n      </td>\n      <td>\n        <p>4</p>\n      </td>\n      <td>\n        <p>E</p>\n      </td>\n    </tr>\n    <tr>\n      <td>\n        <p>Asia</p>\n      </td>\n      <td>\n        <p>9</p>\n      </td>\n      <td>\n        <p>E</p>\n      </td>\n    </tr>\n    <tr>\n      <td>\n        <p>Central Asia</p>\n      </td>\n      <td>\n        <p>1</p>\n      </td>\n      <td>\n        <p>E</p>\n      </td>\n    </tr>\n    <tr>\n      <td>\n        <p>Eastern Asia</p>\n      </td>\n      <td>\n        <p>1</p>\n      </td>\n      <td>\n        <p>E</p>\n      </td>\n    </tr>\n    <tr>\n      <td>\n        <p>Southern Asia</p>\n      </td>\n      <td>\n        <p>4</p>\n      </td>\n      <td>\n        <p>E</p>\n      </td>\n    </tr>\n    <tr>\n      <td>\n        <p>South-Eastern Asia</p>\n      </td>\n      <td>\n        <p>2</p>\n      </td>\n      <td>\n        <p>E</p>\n      </td>\n    </tr>\n    <tr>\n      <td>\n        <p>Western Asia</p>\n      </td>\n      <td>\n        <p>1</p>\n      </td>\n      <td>\n        <p>E</p>\n      </td>\n    </tr>\n    <tr>\n      <td>\n        <p>Europe</p>\n      </td>\n      <td>\n        <p>5</p>\n      </td>\n      <td>\n        <p>E</p>\n      </td>\n    </tr>\n    <tr>\n      <td>\n        <p>Eastern Europe</p>\n      </td>\n      <td>\n        <p>5</p>\n      </td>\n      <td>\n        <p>E</p>\n      </td>\n    </tr>\n    <tr>\n      <td>\n        <p>Northern Europe</p>\n      </td>\n      <td></td>\n      <td></td>\n    </tr>\n    <tr>\n      <td>\n        <p>Southern Europe</p>\n      </td>\n      <td></td>\n      <td></td>\n    </tr>\n    <tr>\n      <td>\n        <p>Western Europe</p>\n      </td>\n      <td></td>\n      <td></td>\n    </tr>\n    <tr>\n      <td>\n        <p>Oceania</p>\n      </td>\n      <td></td>\n      <td></td>\n    </tr>\n    <tr>\n      <td>\n        <p>Australia and New Zealand</p>\n      </td>\n      <td></td>\n      <td></td>\n    </tr>\n    <tr>\n      <td>\n        <p>Melanesia</p>\n      </td>\n      <td></td>\n      <td></td>\n    </tr>\n    <tr>\n      <td>\n        <p>Micronesia</p>\n      </td>\n      <td></td>\n      <td></td>\n    </tr>\n    <tr>\n      <td>\n        <p>Polynesia</p>\n      </td>\n      <td></td>\n      <td></td>\n    </tr>\n  </tbody>\n</table>\n<p><strong>Time series:</strong></p>\n<p>By 2030.</p>\n<p><strong>Disaggregation:</strong></p>\n<p>Indicator 2.3.2 must be disaggregated by classes of farming/pastoral/forestry enterprise size. The overall SDG Target 2.3 requires specific focus on women, indigenous peoples, family farmers, pastoralists and fishers. For this reason, the indicator must be disaggregated by <em>sex, type of enterprise and by community of reference</em>.</p>","es":"","fr":"","pt":"","ru":""}}