<?xml version="1.0" encoding="utf-8"?>
<root>
	<status>success</status>
	<message>The REG_AGG field for indicator 1-1-1a, translated into all languages</message>
	<data>
		<languages>
			<language lang="ru">## Региональные агрегаты

Поскольку в большинстве стран обследования проводятся не каждый год, оценки бедности должны составляться по следующим друг за другом годам путем интерполяции или экстраполяции с использованием данных национальных счетов. Эти оценки по следующим друг за другом годам затем агрегируются в региональные и глобальные данные. Региональные и глобальные показатели являются средневзвешенными по населению.
			</language>
			<language lang="en">## Regional aggregates

Because surveys are not conducted every year in most countries, poverty estimates have to be derived for line-up years by interpolation or extrapolation using national accounts data. These estimates for line-up years are then aggregated to regional and global numbers. Regional and global aggregates are population-weighted averages.
			</language>
</languages>
</data>
</root>
