<?xml version="1.0" encoding="utf-8"?>
<root>
	<status>success</status>
	<message>The UNIT_MEASURE field for indicator 1-1-1a, translated into all languages</message>
	<data>
		<languages>
			<language lang="ar"/>
			<language lang="en">&lt;p&gt;The unit of measure is the proportion of people. &lt;/p&gt;
			</language>
			<language lang="es"/>
			<language lang="fr">&lt;p&gt;L’unité de mesure est la proportion de personnes. &lt;/p&gt;
			</language>
			<language lang="pt"/>
			<language lang="ru"/>
</languages>
</data>
</root>
