<?xml version="1.0" encoding="utf-8"?>
<root>
	<status>success</status>
	<message>The IMPUTATION field for indicator 15-1-1, translated into all languages</message>
	<data>
		<languages>
			<language lang="ru"/>
			<language lang="en">## Treatment of missing values

* At country level

For countries and territories where no information was provided to FAO for FRA 2015 (79 countries and territories representing 1.2 percent of the global forest area), a report was prepared by FAO using existing information from previous assessments and literature search.

* At regional and global levels

See above
			</language>
</languages>
</data>
</root>
