{"status":"success","message":"The CLASS_SYSTEM field for indicator 3-d-1, translated into all languages","data":{"ar":"","en":"<p>We use the WHO Official list of countries that are State Parties of the International Health Regulations (IHR2005) and distributed according to 6 WHO administrative regions (<a href=\"http://www.who.int\">www.who.int</a> ). </p>","es":"","fr":"<p>Nous utilisons la liste officielle de l’OMS des pays qui sont des États parties du Règlement sanitaire international (RSI 2005) et qui sont séparés en 6 régions administratives de l’OMS (<a href=\"https://www.who.int/fr/home\">https://www.who.int/fr/home</a> ). </p>","pt":"","ru":""}}