<?xml version="1.0" encoding="utf-8"?>
<root>
	<status>success</status>
	<message>The REG_AGG field for indicator 7-1-2, translated into all languages</message>
	<data>
		<languages>
			<language lang="ar"/>
			<language lang="en">&lt;h2&gt;Regional aggregates:&lt;/h2&gt;
&lt;p&gt;Regional and global estimates are population-weighted; i.e. the country estimates (e.g. 56%) is multiplied by its population, this figure is summed (by region or for all countries) and divided by the sum of the population of the countries included.&lt;/p&gt;
			</language>
			<language lang="es"/>
			<language lang="fr">&lt;h2&gt;Agrégats régionaux : &lt;/h2&gt;
&lt;p&gt;Les estimations régionales et mondiales sont pondérées en fonction de la population ; c&apos;est-à-dire que les estimations des pays (par exemple 56%) sont multipliées par leur population, ce chiffre est additionné (par région ou pour tous les pays) et divisé par la somme de la population des pays inclus.&lt;/p&gt;
			</language>
			<language lang="ru">&lt;h2&gt;Региональные агрегаты: &lt;/h2&gt;
&lt;p&gt; Региональные и глобальные оценки взвешены на численность населения; т.е. оценка страны (например, 56%) умножается на численность ее население, эта цифра суммируется (по регионам или для всех стран) и делится на общее количество населения включенных стран. &lt;/p&gt;
			</language>
</languages>
</data>
</root>
