<?xml version="1.0" encoding="utf-8"?>
<root>
	<status>success</status>
	<message>The CONTACT_ORGANISATION field for indicator 2-a-1, translated into all languages</message>
	<data>
		<languages>
			<language lang="ar"/>
			<language lang="en">&lt;p&gt;Food and Agriculture Organization of the United Nations (FAO)&lt;/p&gt;
			</language>
			<language lang="es"/>
			<language lang="fr">&lt;p&gt;Organisation des Nations unies pour l&apos;alimentation et l&apos;agriculture (FAO)&lt;/p&gt;
			</language>
			<language lang="pt"/>
			<language lang="ru"/>
</languages>
</data>
</root>
