<?xml version="1.0" encoding="utf-8"?>
<root>
	<status>success</status>
	<message>The SDG_SERIES_DESCR field for indicator 2-a-1, translated into all languages</message>
	<data>
		<languages>
			<language lang="ar"/>
			<language lang="en">&lt;p&gt;Primary series: Agriculture orientation index for government expenditures&lt;/p&gt;
&lt;p&gt;Complementary series: Agriculture value added share of GDP (%)&lt;/p&gt;
&lt;p&gt;Complementary series: Agriculture share of Government Expenditure (%). &lt;/p&gt;
			</language>
			<language lang="es"/>
			<language lang="fr">&lt;p&gt;Série primaire : Indice d’orientation agricole pour les dépenses publiques&lt;/p&gt;
&lt;p&gt;Série complémentaire : Part de la valeur ajoutée de l’agriculture dans le PIB (%)&lt;/p&gt;
&lt;p&gt;Séries complémentaires : Part de l’agriculture dans les dépenses publiques (%). &lt;/p&gt;
			</language>
			<language lang="pt"/>
			<language lang="ru"/>
</languages>
</data>
</root>
