<?xml version="1.0" encoding="utf-8"?>
<root>
	<status>success</status>
	<message>The SDG_SERIES_DESCR field for indicator 15-2-1, translated into all languages</message>
	<data>
		<languages>
			<language lang="ar"/>
			<language lang="en">&lt;p&gt;Annual forest area change rate (%) (AG_LND_FRSTCHG)&lt;/p&gt;
&lt;p&gt;Above-ground biomass in forest (tonnes per hectare) (AG_LND_FRSTBIOPHA)&lt;/p&gt;
&lt;p&gt;Proportion of forest area within legally established protected areas (%) (AG_LND_FRSTPRCT)&lt;/p&gt;
&lt;p&gt;Proportion of forest area with a long-term management plan (%) (AG_LND_FRSTMGT)&lt;/p&gt;
&lt;p&gt;Forest area under an independently verified forest management certification scheme (thousands of hectares) (AG_LND_FRSTCERT)&lt;/p&gt;
			</language>
			<language lang="es"/>
			<language lang="fr"/>
			<language lang="pt"/>
			<language lang="ru"/>
</languages>
</data>
</root>
