<?xml version="1.0" encoding="utf-8"?>
<root>
	<status>success</status>
	<message>The DISAGGREGATION field for indicator 7-1-1, translated into all languages</message>
	<data>
		<languages>
			<language lang="ru">## Дезагрегация

Разбивка данных по доступу к электроэнергии для сельских или городских мест проживания возможна по всем странам.
			</language>
			<language lang="en">## Disaggregation

Disaggregation of access to electricity by rural or urban place of residence is possible for all countries.
			</language>
</languages>
</data>
</root>
