<?xml version="1.0" encoding="utf-8"?>
<root>
	<status>success</status>
	<message>The DOC_METHOD field for indicator 7-1-1, translated into all languages</message>
	<data>
		<languages>
			<language lang="ru"># Наличие данных

По этим показателям за период 1990-2012 гг. были собраны данные более чем по 180 странам мира.
			</language>
			<language lang="en"># Data availability

Data was collected on these indicators for the period 1990-2012 for more than 180 countries worldwide.
			</language>
</languages>
</data>
</root>
