{"status":"success","message":"The FREQ_COLL field for indicator 15-4-2, translated into all languages","data":{"ar":"","en":"<p>SDG indicator 15.4.2 is updated every three years. </p>","es":"<h1>Calendario</h1>\n<h2>Recopilación de datos:</h2>\n<p>La ICC cubierta terrestre de la AEE está disponible desde 1992 hasta 2018. Cada año se entrega un nuevo mapa global de la cubierta terrestre.</p>","fr":"","pt":"","ru":"<h1> Календарь </h1>\n<h2> Сбор данных: </h2>\n<p> Информация по растительному покрову ИИК ЕКА доступна с 1992 по 2018 год. Ежегодно предоставляется новая глобальная карта растительного покрова. </p>"}}