<?xml version="1.0" encoding="utf-8"?>
<root>
	<status>success</status>
	<message>The IMPUTATION field for indicator 17-5-1, translated into all languages</message>
	<data>
		<languages>
			<language lang="ar"/>
			<language lang="en">&lt;p&gt;&lt;strong&gt;&amp;#x2022; At country level&lt;/strong&gt;&lt;/p&gt;
&lt;p&gt;UNCTAD&amp;#x2019;s research complements annual surveys in cases where information from official government websites confirms that an outward investment promotion scheme is in place, but the concerned country has not responded to the survey.&lt;/p&gt;
&lt;p&gt;&lt;strong&gt;&amp;#x2022; At regional and global levels&lt;/strong&gt;&lt;/p&gt;
&lt;p&gt;In order to calculate regional and global levels, missing data may be estimated using information from international sources (e.g. OECD and UNCTAD databases).&lt;/p&gt;
&lt;p&gt; Such data may only be available in an aggregated form.&lt;/p&gt;
			</language>
			<language lang="es"/>
			<language lang="fr"/>
			<language lang="pt"/>
			<language lang="ru"/>
</languages>
</data>
</root>
