{"status":"success","message":"The SDG_SERIES_DESCR field for indicator 3-7-1, translated into all languages","data":{"ar":"","en":"<p>Proportion of women of reproductive age (aged 15-49 years) who have their need for family planning satisfied with modern methods (% of women aged 15-49 years)</p>","es":"","fr":"<p>Proportion de femmes en âge de procréer (âgées de 15 à 49 ans) dont le besoin de planification familiale est satisfait avec des méthodes modernes (% des femmes âgées de 15 à 49 ans)</p>","pt":"","ru":""}}