<?xml version="1.0" encoding="utf-8"?>
<root>
	<status>success</status>
	<message>The FREQ_COLL field for indicator 3-3-5, translated into all languages</message>
	<data>
		<languages>
			<language lang="ar"/>
			<language lang="en">&lt;p&gt;2019 data is being collected throughout Q2 and Q3 of 2020. &lt;/p&gt;
			</language>
			<language lang="es">&lt;h1&gt;Calendario&lt;/h1&gt;
&lt;h2&gt;Recopilación de datos:&lt;/h2&gt;
&lt;p&gt;Los datos de 2018 se están recogiendo a lo largo del segundo y tercer trimestre de 2019. &lt;/p&gt;
			</language>
			<language lang="fr">&lt;p&gt;Les données de 2019 sont recueillies tout au long des deuxième et troisième trimestres de 2020. &lt;/p&gt;
			</language>
			<language lang="pt"/>
			<language lang="ru">&lt;h1&gt; Календарь &lt;/h1&gt;
&lt;h2&gt; Сбор данных: &lt;/h2&gt;
&lt;p&gt; Данные за 2018 год собираются в течение второго и третьего кварталов 2019 года. &lt;/p&gt;
			</language>
</languages>
</data>
</root>
