{"status":"success","message":"The ADJUSTMENT field for indicator 3-3-4, translated into all languages","data":{"ar":"","en":"<p>Estimates are provided for the 194 WHO Member States and grouped accordingly to the six WHO regions. We also provide estimates according to income classification and follow UN Regional Groupings and Compositions as much as possible. </p>","es":"","fr":"<p>Des estimations sont fournies pour les 194 États membres de l’OMS et regroupées en fonction des six régions de l’OMS. Nous fournissons également des estimations selon la classification des revenus et suivons autant que possible les groupements et compositions régionaux des Nations Unies. </p>","pt":"","ru":""}}