<?xml version="1.0" encoding="utf-8"?>
<root>
	<status>success</status>
	<message>The DATA_COMP field for indicator 1-a-2, translated into all languages</message>
	<data>
		<languages>
			<language lang="ar"/>
			<language lang="en">&lt;p&gt;Total government expenditure on education in all levels combined is expressed as a percentage of total general government expenditure (all sectors).&lt;/p&gt;
&lt;p&gt;&lt;math xmlns=&quot;http://www.w3.org/1998/Math/MathML&quot;&gt;
    &lt;msub&gt;
      &lt;mrow&gt;
        &lt;mi&gt;P&lt;/mi&gt;
        &lt;mi&gt;X&lt;/mi&gt;
        &lt;mi&gt;E&lt;/mi&gt;
      &lt;/mrow&gt;
      &lt;mrow&gt;
        &lt;mi&gt;t&lt;/mi&gt;
      &lt;/mrow&gt;
    &lt;/msub&gt;
    &lt;mo&gt;=&lt;/mo&gt;
    &lt;mfrac&gt;
      &lt;mrow&gt;
        &lt;mi&gt;T&lt;/mi&gt;
        &lt;msub&gt;
          &lt;mrow&gt;
            &lt;mi&gt;X&lt;/mi&gt;
            &lt;mi&gt;E&lt;/mi&gt;
          &lt;/mrow&gt;
          &lt;mrow&gt;
            &lt;mi&gt;t&lt;/mi&gt;
          &lt;/mrow&gt;
        &lt;/msub&gt;
      &lt;/mrow&gt;
      &lt;mrow&gt;
        &lt;msub&gt;
          &lt;mrow&gt;
            &lt;mi&gt;T&lt;/mi&gt;
            &lt;mi&gt;P&lt;/mi&gt;
            &lt;mi&gt;X&lt;/mi&gt;
          &lt;/mrow&gt;
          &lt;mrow&gt;
            &lt;mi&gt;t&lt;/mi&gt;
          &lt;/mrow&gt;
        &lt;/msub&gt;
      &lt;/mrow&gt;
    &lt;/mfrac&gt;
  &lt;/math&gt;&lt;/p&gt;
&lt;p&gt;&lt;math xmlns=&quot;http://www.w3.org/1998/Math/MathML&quot;&gt;
    &lt;msub&gt;
      &lt;mrow&gt;
        &lt;mi&gt;P&lt;/mi&gt;
        &lt;mi&gt;X&lt;/mi&gt;
        &lt;mi&gt;E&lt;/mi&gt;
      &lt;/mrow&gt;
      &lt;mrow&gt;
        &lt;mi&gt;t&lt;/mi&gt;
      &lt;/mrow&gt;
    &lt;/msub&gt;
  &lt;/math&gt; = government expenditure on education as a percentage of total government expenditure in financial year &lt;em&gt;t&lt;/em&gt;&lt;/p&gt;
&lt;p&gt;&lt;math xmlns=&quot;http://www.w3.org/1998/Math/MathML&quot;&gt;
    &lt;msub&gt;
      &lt;mrow&gt;
        &lt;mi&gt;T&lt;/mi&gt;
        &lt;mi&gt;X&lt;/mi&gt;
        &lt;mi&gt;E&lt;/mi&gt;
      &lt;/mrow&gt;
      &lt;mrow&gt;
        &lt;mi&gt;t&lt;/mi&gt;
      &lt;/mrow&gt;
    &lt;/msub&gt;
  &lt;/math&gt; = total general government expenditure on education in financial year &lt;em&gt;t&lt;/em&gt;&lt;/p&gt;
&lt;p&gt;&lt;math xmlns=&quot;http://www.w3.org/1998/Math/MathML&quot;&gt;
    &lt;msub&gt;
      &lt;mrow&gt;
        &lt;mi&gt;T&lt;/mi&gt;
        &lt;mi&gt;P&lt;/mi&gt;
        &lt;mi&gt;X&lt;/mi&gt;
      &lt;/mrow&gt;
      &lt;mrow&gt;
        &lt;mi&gt;t&lt;/mi&gt;
      &lt;/mrow&gt;
    &lt;/msub&gt;
  &lt;/math&gt; = total government expenditure in financial year &lt;em&gt;t&lt;/em&gt;&lt;/p&gt;
&lt;p&gt;Note: the numerator and denominator should come from the same source as preferred option.&lt;/p&gt;
			</language>
			<language lang="es"/>
			<language lang="fr">&lt;p&gt;Les dépenses publiques totales en éducation (tous niveaux confondus) sont exprimées en pourcentage des dépenses publiques totales (tous secteurs confondus).&lt;/p&gt;
&lt;p&gt;&lt;math xmlns=&quot;http://www.w3.org/1998/Math/MathML&quot;&gt;
    &lt;msub&gt;
      &lt;mrow&gt;
        &lt;mi&gt;P&lt;/mi&gt;
        &lt;mi&gt;X&lt;/mi&gt;
        &lt;mi&gt;E&lt;/mi&gt;
      &lt;/mrow&gt;
      &lt;mrow&gt;
        &lt;mi&gt;t&lt;/mi&gt;
      &lt;/mrow&gt;
    &lt;/msub&gt;
    &lt;mo&gt;=&lt;/mo&gt;
    &lt;mfrac&gt;
      &lt;mrow&gt;
        &lt;mi&gt;T&lt;/mi&gt;
        &lt;msub&gt;
          &lt;mrow&gt;
            &lt;mi&gt;X&lt;/mi&gt;
            &lt;mi&gt;E&lt;/mi&gt;
          &lt;/mrow&gt;
          &lt;mrow&gt;
            &lt;mi&gt;t&lt;/mi&gt;
          &lt;/mrow&gt;
        &lt;/msub&gt;
      &lt;/mrow&gt;
      &lt;mrow&gt;
        &lt;msub&gt;
          &lt;mrow&gt;
            &lt;mi&gt;T&lt;/mi&gt;
            &lt;mi&gt;P&lt;/mi&gt;
            &lt;mi&gt;X&lt;/mi&gt;
          &lt;/mrow&gt;
          &lt;mrow&gt;
            &lt;mi&gt;t&lt;/mi&gt;
          &lt;/mrow&gt;
        &lt;/msub&gt;
      &lt;/mrow&gt;
    &lt;/mfrac&gt;
  &lt;/math&gt;&lt;/p&gt;
&lt;p&gt;&lt;math xmlns=&quot;http://www.w3.org/1998/Math/MathML&quot;&gt;
    &lt;msub&gt;
      &lt;mrow&gt;
        &lt;mi&gt;P&lt;/mi&gt;
        &lt;mi&gt;X&lt;/mi&gt;
        &lt;mi&gt;E&lt;/mi&gt;
      &lt;/mrow&gt;
      &lt;mrow&gt;
        &lt;mi&gt;t&lt;/mi&gt;
      &lt;/mrow&gt;
    &lt;/msub&gt;
  &lt;/math&gt; = dépenses publiques en éducation exprimées en pourcentage des dépenses publiques totales dans l&apos;année financière &lt;em&gt;t&lt;/em&gt;&lt;/p&gt;
&lt;p&gt;&lt;math xmlns=&quot;http://www.w3.org/1998/Math/MathML&quot;&gt;
    &lt;msub&gt;
      &lt;mrow&gt;
        &lt;mi&gt;T&lt;/mi&gt;
        &lt;mi&gt;X&lt;/mi&gt;
        &lt;mi&gt;E&lt;/mi&gt;
      &lt;/mrow&gt;
      &lt;mrow&gt;
        &lt;mi&gt;t&lt;/mi&gt;
      &lt;/mrow&gt;
    &lt;/msub&gt;
  &lt;/math&gt; = dépenses publiques totales en éducation dans l&apos;année financière &lt;em&gt;t&lt;/em&gt;&lt;/p&gt;
&lt;p&gt;&lt;math xmlns=&quot;http://www.w3.org/1998/Math/MathML&quot;&gt;
    &lt;msub&gt;
      &lt;mrow&gt;
        &lt;mi&gt;T&lt;/mi&gt;
        &lt;mi&gt;P&lt;/mi&gt;
        &lt;mi&gt;X&lt;/mi&gt;
      &lt;/mrow&gt;
      &lt;mrow&gt;
        &lt;mi&gt;t&lt;/mi&gt;
      &lt;/mrow&gt;
    &lt;/msub&gt;
  &lt;/math&gt; = dépenses publiques totales dans l&apos;année financière &lt;em&gt;t&lt;/em&gt;&lt;/p&gt;
&lt;p&gt;Remarque : l’option préférée est que le numérateur et le dénominateur proviennent de la même source. &lt;/p&gt;
			</language>
			<language lang="pt"/>
			<language lang="ru"/>
</languages>
</data>
</root>
