<?xml version="1.0" encoding="utf-8"?>
<root>
	<status>success</status>
	<message>The SDG_CUSTODIAN_AGENCIES field for indicator 9-1-2, translated into all languages</message>
	<data>
		<languages>
			<language lang="ar"/>
			<language lang="en">&lt;h1&gt;Institutional information&lt;/h1&gt;
&lt;h2&gt;Organization(s):&lt;/h2&gt;
&lt;p&gt;International Civil Aviation Organization (ICAO); International Transport Forum (ITF); United Nations Economic Commission for Europe (UNECE); United Nations Conference on Trade and Development (UNCTAD).&lt;/p&gt;
			</language>
			<language lang="es"/>
			<language lang="fr">&lt;h1&gt;Informations institutionnelles &lt;/h1&gt;
&lt;h2&gt;Organisation (s): &lt;/h2&gt;
&lt;p&gt;Organisation de l&apos;aviation civile internationale (OACI); Forum international des transports (ITF); Commission économique des Nations Unies pour l&apos;Europe (CEE-ONU); Conférence des Nations Unies sur le commerce et le développement (CNUCED). &lt;/p&gt;
			</language>
			<language lang="pt"/>
			<language lang="ru">&lt;h1&gt; Институциональная информация &lt;/h1&gt;
&lt;h2&gt; Организация (и): &lt;/h2&gt;
&lt;p&gt; Международная организация гражданской авиации (ИКАО); Международный транспортный форум (МТФ); Европейская экономическая комиссия ООН (ЕЭК ООН); Конференция Организации Объединенных Наций по торговле и развитию (ЮНКТАД). &lt;/p&gt;
			</language>
</languages>
</data>
</root>
