<?xml version="1.0" encoding="utf-8"?>
<root>
	<status>success</status>
	<message>The DATA_SOURCE field for indicator 8-5-2, translated into all languages</message>
	<data>
		<languages>
			<language lang="ar"/>
			<language lang="en">&lt;h1&gt;Data providers&lt;/h1&gt;
&lt;p&gt;Mainly national statistical offices, and in some cases labour ministries or other related agencies, at the country-level. In some cases, regional or international statistical offices can also act as data providers.&lt;/p&gt;
			</language>
			<language lang="es"/>
			<language lang="fr">&lt;h1&gt;Fournisseurs de données&lt;/h1&gt;
&lt;p&gt;Principalement les bureaux nationaux de statistiques et, dans certains cas, les ministères du travail ou d&apos;autres organismes connexes, au niveau national. Dans certains cas, les bureaux de statistiques régionaux ou internationaux peuvent également agir en tant que fournisseurs de données.&lt;/p&gt;
			</language>
			<language lang="ru"/>
</languages>
</data>
</root>
