<?xml version="1.0" encoding="utf-8"?>
<root>
	<status>success</status>
	<message>The OTHER_DOC field for indicator 5-6-2, translated into all languages</message>
	<data>
		<languages>
			<language lang="ar"/>
			<language lang="en">&lt;p&gt;&lt;a href=&quot;https://www.unfpa.org/sdg-5-6&quot;&gt;https://www.unfpa.org/sdg-5-6&lt;/a&gt; &lt;/p&gt;
&lt;p&gt;&lt;strong&gt;References:&lt;/strong&gt;&lt;/p&gt;
&lt;p&gt;United Nations (1994) International Conference on Population and Development: Programme of Action. Cairo, Egypt.&lt;/p&gt;
&lt;p&gt;United Nations (1995) Fourth World Conference on Women: Programme of Action. Beijing, China.&lt;/p&gt;
&lt;p&gt;CEDAW General Recommendation no. 24. Accessed online 24 May 2018: &lt;a href=&quot;http://www.refworld.org/docid/453882a73.html&quot;&gt;http://www.refworld.org/docid/453882a73.html&lt;/a&gt;; CEDAW General Comment no. 35 (2017). Accessed online 23&lt;sup&gt; &lt;/sup&gt;May 2018: &lt;a href=&quot;http://tbinternet.ohchr.org/Treaties/CEDAW/Shared%20Documents/1_Global/CEDAW_C_GC_35_8267_E.pdf&quot;&gt;http://tbinternet.ohchr.org/Treaties/CEDAW/Shared%20Documents/1_Global/CEDAW_C_GC_35_8267_E.pdf&lt;/a&gt;; CESCR General Comment no. 14. Accessed online 23 May 2018: &lt;a href=&quot;http://www.refworld.org/pdfid/4538838d0.pdf&quot;&gt;http://www.refworld.org/pdfid/4538838d0.pdf&lt;/a&gt;; CESCR General Comment no. 20. Accessed 24 May 2018: &lt;a href=&quot;http://www.refworld.org/docid/4a60961f2.html&quot;&gt;http://www.refworld.org/docid/4a60961f2.html&lt;/a&gt;; &lt;a href=&quot;https://www.escr-net.org/resources/general-comment-no-22-2016-right-sexual-and-reproductive-health#_ftn44&quot; target=&quot;_blank&quot;&gt;C&lt;/a&gt;ESCR General Comment no. 22. Accessed online 23&lt;sup&gt; &lt;/sup&gt;May 2018: &lt;a href=&quot;https://www.escr-net.org/resources/general-comment-no-22-2016-right-sexual-and-reproductive-health&quot;&gt;https://www.escr-net.org/resources/general-comment-no-22-2016-right-sexual-and-reproductive-health&lt;/a&gt;; CRC General Comment No. 15. Accessed 24 May 2018: &lt;a href=&quot;http://www.refworld.org/docid/51ef9e134.html&quot;&gt;http://www.refworld.org/docid/51ef9e134.html&lt;/a&gt;; CRPD Articles 23 and 25. Accessed online 24 May 2018: &lt;a href=&quot;https://www.un.org/development/desa/disabilities/convention-on-the-rights-of-persons-with-disabilities/convention-on-the-rights-of-persons-with-disabilities-2.html&quot;&gt;https://www.un.org/development/desa/disabilities/convention-on-the-rights-of-persons-with-disabilities/convention-on-the-rights-of-persons-with-disabilities-2.html&lt;/a&gt;. &lt;/p&gt;
			</language>
			<language lang="es"/>
			<language lang="fr">&lt;p&gt;&lt;a href=&quot;https://www.unfpa.org/sdg-5-6&quot;&gt;(en anglais) https://www.unfpa.org/sdg-5-6&lt;/a&gt; &lt;/p&gt;
&lt;p&gt;&lt;strong&gt;Références :&lt;/strong&gt;&lt;/p&gt;
&lt;p&gt;Nations Unies (1994) Conférence internationale sur la population et le développement : Programme d&apos;action. Le Caire, Egypte.&lt;/p&gt;
&lt;p&gt;Nations Unies (1995) Quatrième Conférence mondiale sur les femmes : Programme d&apos;action. Beijing, Chine.&lt;/p&gt;
&lt;p&gt;Convention sur l&apos;élimination de toutes les formes de discrimination à l&apos;égard des femmes (CEDEF) - Recommandation générale n°24. Consultée en ligne le 24 mai 2018 : &lt;a href=&quot;https://www.refworld.org/cgi-bin/texis/vtx/rwmain/opendocpdf.pdf?reldoc=y&amp;docid=52d906264
&quot;&gt;https://www.refworld.org/cgi-bin/texis/vtx/rwmain/opendocpdf.pdf?reldoc=y&amp;docid=52d906264&lt;/a&gt;&lt;/p&gt;
&lt;p&gt;CEDEF - Observation générale n° 35 (2017). Consultée en ligne le 23 mai 2018 : &lt;a href=&quot;https://tbinternet.ohchr.org/_layouts/15/treatybodyexternal/Download.aspx?symbolno=CEDAW/C/GC/35&amp;Lang=fr&quot;&gt;https://tbinternet.ohchr.org/_layouts/15/treatybodyexternal/Download.aspx?symbolno=CEDAW/C/GC/35&amp;Lang=fr&lt;/a&gt;&lt;/p&gt;
&lt;p&gt;Observation générale n° 14 du Comité des droits économiques, sociaux et culturels (CDESC). Consultée en ligne le 23 mai 2018 : &lt;a href=&quot;https://www.refworld.org/cgi-bin/texis/vtx/rwmain/opendocpdf.pdf?reldoc=y&amp;docid=47ebcc2f2&quot;&gt;https://www.refworld.org/cgi-bin/texis/vtx/rwmain/opendocpdf.pdf?reldoc=y&amp;docid=47ebcc2f2&lt;/a&gt;&lt;/p&gt;
&lt;p&gt;Observation générale n° 20 du CDESC. Consultée le 24 mai 2018 : &lt;a href=&quot;https://www.refworld.org/cgi-bin/texis/vtx/rwmain/opendocpdf.pdf?reldoc=y&amp;docid=4ae049912&quot;&gt;https://www.refworld.org/cgi-bin/texis/vtx/rwmain/opendocpdf.pdf?reldoc=y&amp;docid=4ae049912&lt;/a&gt;&lt;/p&gt;
&lt;p&gt;Observation générale n° 22 du CDESC. Consultée en ligne le 23 mai 2018 : &lt;a href=&quot;https://www.escr-net.org/resources/general-comment-no-22-2016-right-sexual-and-reproductive-health&quot;&gt;(en anglais) https://www.escr-net.org/resources/general-comment-no-22-2016-right-sexual-and-reproductive-health&lt;/a&gt;&lt;/p&gt;
&lt;p&gt;Observation générale n°15 du Comité des droits de l&apos;enfant. Consultée le 24 mai 2018 : &lt;a href=&quot;http://www.refworld.org/docid/51ef9e134.html&quot;&gt;(en anglais) http://www.refworld.org/docid/51ef9e134.html&lt;/a&gt;&lt;/p&gt;
&lt;p&gt;Convention relative aux droits des personnes handicapées (CDPH), articles 23 et 25. Consultée en ligne le 24 mai 2018 : &lt;a href=&quot;https://digitallibrary.un.org/record/588742/files/A_RES_61_106-FR.pdf&quot;&gt;https://digitallibrary.un.org/record/588742/files/A_RES_61_106-FR.pdf&lt;/a&gt;&lt;/p&gt;
			</language>
			<language lang="pt"/>
			<language lang="ru"/>
</languages>
</data>
</root>
