<?xml version="1.0" encoding="utf-8"?>
<root>
	<status>success</status>
	<message>The REL_CAL_POLICY field for indicator 3-1-2, translated into all languages</message>
	<data>
		<languages>
			<language lang="ar"/>
			<language lang="es"/>
			<language lang="fr">&lt;h2&gt; Publication des données :&lt;/h2&gt;
&lt;p&gt; Les estimations sont publiées chaque année, en mai, par l’OMS dans World Health Statistics (&lt;a href=&quot;http://www.who.int/whosis/whostat/en/&quot;&gt;http://www.who.int/whosis/whostat/fr/&lt;/a&gt;) et par l’UNICEF dans State of the World&amp;#x2019;s Children, et sont disponibles au &lt;a href=&quot;http://www.data.unicef.org&quot;&gt;www.data.unicef.org&lt;/a&gt;&lt;/p&gt;
			</language>
			<language lang="ru">&lt;h2&gt; Выпуск данных: &lt;/h2&gt;
&lt;p&gt; Оценки публикуются ВОЗ в докладе &quot;Мировая статистика здравоохранения&quot;, выходящем ежегодно в мае (&lt;a href=&quot;http://www.who.int/whosis/whostat/en/&quot;&gt;http://www.who.int/whosis/whostat/en/&lt;/a&gt;) и ЮНИСЕФ в докладе &quot;Состояние детей в мире&quot;, доступном по адресу &lt;a href=&quot;http://www.data.unicef.org&quot;&gt;www.data.unicef.org&lt;/a&gt; &lt;/p&gt;
			</language>
			<language lang="en">&lt;h2&gt;Data release:&lt;/h2&gt;
&lt;p&gt;Estimates are published annually, in May by WHO in World Health Statistics (&lt;a href=&quot;http://www.who.int/whosis/whostat/en/&quot;&gt;http://www.who.int/whosis/whostat/en/&lt;/a&gt;) and by UNICEF in State of the World&amp;#x2019;s Children, and are available at &lt;a href=&quot;http://www.data.unicef.org&quot;&gt;www.data.unicef.org&lt;/a&gt;&lt;/p&gt;
			</language>
</languages>
</data>
</root>
