<?xml version="1.0" encoding="utf-8"?>
<root>
	<status>success</status>
	<message>The SDG_TARGET field for indicator 2-a-2, translated into all languages</message>
	<data>
		<languages>
			<language lang="ar"/>
			<language lang="en">&lt;p&gt;Target 2.a: Increase investment, including through enhanced international cooperation, in rural infrastructure, agricultural research and extension services, technology development and plant and livestock gene banks in order to enhance agricultural productive capacity in developing countries, in particular least developed countries&lt;/p&gt;
			</language>
			<language lang="es">&lt;p&gt;Meta 2.a: Aumentar, incluso mediante una mayor cooperación internacional, las inversiones en infraestructura rural, investigación y servicios de extensión agrícola, desarrollo tecnológico y bancos de genes de plantas y ganado a fin de mejorar la capacidad de producción agropecuaria en los países en desarrollo, particularmente en los países menos adelantados&lt;/p&gt;
			</language>
			<language lang="fr">&lt;p&gt;Cible 2.a : Accroître, notamment grâce au renforcement de la coopération internationale, l’investissement dans l’infrastructure rurale, les services de recherche et de vulgarisation agricoles et la mise au point de technologies et de banques de plantes et de gènes d’animaux d’élevage, afin de renforcer les capacités productives agricoles des pays en développement, en particulier des pays les moins avancés&lt;/p&gt;
			</language>
			<language lang="pt"/>
			<language lang="ru">&lt;p&gt;Задача 2.a: Увеличить инвестирование, в том числе посредством активизации международного сотрудничества, в сельскую инфраструктуру, сельскохозяйственные исследования и агропропаганду, развитие технологий и создание генетических банков растений и животных в целях укрепления потенциала развивающихся стран, особенно наименее развитых стран, в области сельскохозяйственного производства&lt;/p&gt;
			</language>
</languages>
</data>
</root>
