<?xml version="1.0" encoding="utf-8"?>
<root>
	<status>success</status>
	<message>The DATA_COMP field for indicator 9-5-2, translated into all languages</message>
	<data>
		<languages>
			<language lang="ar"/>
			<language lang="en">&lt;p&gt;Computation of the indicator Researchers (in full-time equivalent) per million inhabitants uses available population data as denominator.&lt;/p&gt;
			</language>
			<language lang="es">&lt;h1&gt;Metodología&lt;/h1&gt;
&lt;h2&gt;Método de cálculo:&lt;/h2&gt;
&lt;p&gt;El cálculo del indicador Investigadores (en equivalente a tiempo completo) por millón de habitantes utiliza como denominador los datos de población disponibles.&lt;/p&gt;
			</language>
			<language lang="fr">&lt;h1&gt; Méthodologie&lt;/h1&gt;
&lt;h2&gt; Méthode de calcul:&lt;/h2&gt;
&lt;p&gt; Calcul de l’indicateur Les chercheurs (en équivalent temps plein) par million d’habitants utilisent les données démographiques disponibles comme dénominateur. &lt;/p&gt;
			</language>
			<language lang="pt"/>
			<language lang="ru">&lt;h1&gt; Методология &lt;/h1&gt;
&lt;h2&gt; Метод расчета: &lt;/h2&gt;
&lt;p&gt; При вычислении количества исследователей (в эквиваленте полной занятости), приходящихся на миллион жителей, используют имеющиеся данные по населению в качестве знаменателя. &lt;/p&gt;
			</language>
</languages>
</data>
</root>
